pythonsql/__init__.py
pythonsql/column.py
pythonsql/common.py
pythonsql/database.py
pythonsql/table.py
wildev_pysql-1.0.0.dist-info/METADATA
wildev_pysql-1.0.0.dist-info/WHEEL
wildev_pysql-1.0.0.dist-info/top_level.txt
wildev_pysql-1.0.0.dist-info/RECORD
